docling_serve/__init__.py
docling_serve/__main__.py
docling_serve/app.py
docling_serve/auth.py
docling_serve/gradio_ui.py
docling_serve/helper_functions.py
docling_serve/orchestrator_factory.py
docling_serve/otel_instrumentation.py
docling_serve/py.typed
docling_serve/response_preparation.py
docling_serve/rq_instrumentation.py
docling_serve/rq_job_wrapper.py
docling_serve/rq_metrics_collector.py
docling_serve/rq_worker_instrumented.py
docling_serve/settings.py
docling_serve/storage.py
docling_serve/websocket_notifier.py
docling_serve/datamodel/__init__.py
docling_serve/datamodel/convert.py
docling_serve/datamodel/requests.py
docling_serve/datamodel/responses.py
docling_serve-1.10.0.dist-info/licenses/LICENSE
docling_serve-1.10.0.dist-info/METADATA
docling_serve-1.10.0.dist-info/WHEEL
docling_serve-1.10.0.dist-info/entry_points.txt
docling_serve-1.10.0.dist-info/top_level.txt
docling_serve-1.10.0.dist-info/RECORD
