Metadata-Version: 2.4
Name: docling-serve
Version: 1.10.0
Summary: Running Docling as a service
Author-email: Michele Dolfi <dol@zurich.ibm.com>, Guillaume Moutier <gmoutier@redhat.com>, Anil Vishnoi <avishnoi@redhat.com>, Panos Vagenas <pva@zurich.ibm.com>, Christoph Auer <cau@zurich.ibm.com>, Peter Staar <taa@zurich.ibm.com>
Maintainer-email: Michele Dolfi <dol@zurich.ibm.com>, Anil Vishnoi <avishnoi@redhat.com>, Panos Vagenas <pva@zurich.ibm.com>, Christoph Auer <cau@zurich.ibm.com>, Peter Staar <taa@zurich.ibm.com>
License: MIT
Project-URL: Homepage, https://github.com/docling-project/docling-serve
Project-URL: Repository, https://github.com/docling-project/docling-serve
Project-URL: Issues, https://github.com/docling-project/docling-serve/issues
Project-URL: Changelog, https://github.com/docling-project/docling-serve/blob/main/CHANGELOG.md
Classifier: License :: OSI Approved :: MIT License
Classifier: Operating System :: OS Independent
Classifier: Development Status :: 5 - Production/Stable
Classifier: Intended Audience :: Developers
Classifier: Typing :: Typed
Classifier: Programming Language :: Python :: 3
Classifier: Programming Language :: Python :: 3.10
Classifier: Programming Language :: Python :: 3.11
Classifier: Programming Language :: Python :: 3.12
Classifier: Programming Language :: Python :: 3.13
Requires-Python: >=3.10
License-File: LICENSE
Requires-Dist: docling~=2.38
Requires-Dist: docling-core>=2.45.0
Requires-Dist: docling-jobkit[kfp,rq,vlm]<2.0.0,>=1.8.0
Requires-Dist: fastapi[standard]<0.129.0
Requires-Dist: httpx~=0.28
Requires-Dist: pydantic~=2.10
Requires-Dist: pydantic-settings~=2.4
Requires-Dist: python-multipart<0.1.0,>=0.0.14
Requires-Dist: typer~=0.12
Requires-Dist: uvicorn[standard]<1.0.0,>=0.29.0
Requires-Dist: websockets~=14.0
Requires-Dist: scalar-fastapi>=1.0.3
Requires-Dist: docling-mcp>=1.0.0
Requires-Dist: opentelemetry-api<2.0.0,>=1.36.0
Requires-Dist: opentelemetry-sdk<2.0.0,>=1.36.0
Requires-Dist: opentelemetry-exporter-otlp>=1.15.0
Requires-Dist: opentelemetry-instrumentation-fastapi<0.58,>=0.57b0
Requires-Dist: opentelemetry-exporter-prometheus>=0.57b0
Requires-Dist: prometheus-client>=0.21.0
Provides-Extra: ui
Requires-Dist: gradio<6.0.0,>=5.23.2; extra == "ui"
Provides-Extra: tesserocr
Requires-Dist: tesserocr~=2.7; extra == "tesserocr"
Provides-Extra: easyocr
Requires-Dist: easyocr>=1.7; extra == "easyocr"
Provides-Extra: rapidocr
Requires-Dist: rapidocr<4.0.0,>=3.3; python_version < "3.14" and extra == "rapidocr"
Requires-Dist: onnxruntime<2.0.0,>=1.7.0; extra == "rapidocr"
Provides-Extra: flash-attn
Requires-Dist: flash-attn~=2.8.2; (sys_platform == "linux" and platform_machine == "x86_64") and extra == "flash-attn"
Dynamic: license-file
